[{"id":1,"message":"error -> A Beautiful Day in the Neighborhood is not seen"},{"id":2,"message":"error -> Legends of the Fall is not seen"},{"id":3,"message":"error -> Legends of the Fall is not seen"},{"id":4,"message":"error -> Legends of the Fall is not seen"},{"id":5,"message":"error -> Killing Eve is not seen"},{"id":6,"message":"error -> Killing Eve is not seen"},{"id":7,"message":"success -> Falsa Identidad was rated with 5.0 by debonairMackerel0"},{"id":8,"message":"error -> Killing Eve is not seen"},{"id":9,"message":"error -> Killing Eve is not seen"}]